{
  "track_id": "audio.000/4G/4gT03zyHBC3ushZZ16gGFK.mp3",
  "relative_path": "audio.000/4G/4gT03zyHBC3ushZZ16gGFK.mp3",
  "duration_seconds": 30.0,
  "source_sample_rate": 44100,
  "tempo_bpm": 125.9104232788086,
  "loudness_lufs": -9.021172523498535,
  "danceability_prob": 0.9996751546859741,
  "voice_prob": 0.9944864511489868,
  "instrumental_prob": 0.005513455718755722,
  "voice_label": "voice",
  "key_profiles": {
    "temperley": {
      "key": "D",
      "scale": "major",
      "strength": 0.669211208820343
    },
    "krumhansl": {
      "key": "E",
      "scale": "minor",
      "strength": 0.6081276535987854
    },
    "edma": {
      "key": "E",
      "scale": "minor",
      "strength": 0.7276836037635803
    }
  },
  "style_activations": {
    "Blues---Boogie Woogie": 1.944222915994942e-08,
    "Blues---Chicago Blues": 9.825093911786098e-07,
    "Blues---Country Blues": 1.8487554598323186e-06,
    "Blues---Delta Blues": 1.0888927590713138e-06,
    "Blues---Electric Blues": 1.674887607805431e-05,
    "Blues---Harmonica Blues": 1.0480761147846351e-06,
    "Blues---Jump Blues": 6.570128618932358e-08,
    "Blues---Louisiana Blues": 1.4895805122705497e-07,
    "Blues---Modern Electric Blues": 2.9218161216704175e-05,
    "Blues---Piano Blues": 9.17761917662574e-06,
    "Blues---Rhythm & Blues": 0.00011423374235164374,
    "Blues---Texas Blues": 7.493417797377333e-08,
    "Brass & Military---Brass Band": 1.8634189302701998e-08,
    "Brass & Military---Marches": 8.245936378159513e-09,
    "Brass & Military---Military": 6.159945886707874e-09,
    "Children's---Educational": 1.529181758996856e-06,
    "Children's---Nursery Rhymes": 3.5728899092646316e-05,
    "Children's---Story": 1.5897555840638233e-06,
    "Classical---Baroque": 1.6602584196334647e-07,
    "Classical---Choral": 1.3490939032578808e-08,
    "Classical---Classical": 5.7572179912313e-07,
    "Classical---Contemporary": 1.6620958831481403e-06,
    "Classical---Impressionist": 3.4932888581806765e-08,
    "Classical---Medieval": 7.630087850429845e-08,
    "Classical---Modern": 1.3093979305267567e-06,
    "Classical---Neo-Classical": 1.197169149236288e-05,
    "Classical---Neo-Romantic": 1.9790411442954792e-07,
    "Classical---Opera": 1.0886783456953708e-06,
    "Classical---Post-Modern": 4.717642809737299e-08,
    "Classical---Renaissance": 5.093086841156946e-08,
    "Classical---Romantic": 3.9298658549569154e-08,
    "Electronic---Abstract": 0.0004085189721081406,
    "Electronic---Acid": 7.605882728967117e-06,
    "Electronic---Acid House": 3.139115506201051e-05,
    "Electronic---Acid Jazz": 0.00012742570834234357,
    "Electronic---Ambient": 0.019781960174441338,
    "Electronic---Bassline": 0.007701047696173191,
    "Electronic---Beatdown": 8.440131932729855e-05,
    "Electronic---Berlin-School": 3.7588661143672653e-06,
    "Electronic---Big Beat": 0.0005084917647764087,
    "Electronic---Bleep": 2.884796401758649e-07,
    "Electronic---Breakbeat": 0.0006804009317420423,
    "Electronic---Breakcore": 6.643172582698753e-06,
    "Electronic---Breaks": 0.0003930180100724101,
    "Electronic---Broken Beat": 0.0011500285472720861,
    "Electronic---Chillwave": 0.008875332772731781,
    "Electronic---Chiptune": 7.420240581268445e-05,
    "Electronic---Dance-pop": 0.03952079638838768,
    "Electronic---Dark Ambient": 9.196724568028003e-05,
    "Electronic---Darkwave": 8.910466567613184e-05,
    "Electronic---Deep House": 0.016086839139461517,
    "Electronic---Deep Techno": 8.226900536101311e-05,
    "Electronic---Disco": 0.00034614279866218567,
    "Electronic---Disco Polo": 1.0044215741800144e-05,
    "Electronic---Donk": 5.937397986599535e-07,
    "Electronic---Downtempo": 0.010330519638955593,
    "Electronic---Drone": 1.1765964700316545e-06,
    "Electronic---Drum n Bass": 0.0013879424659535289,
    "Electronic---Dub": 0.00018494624237064272,
    "Electronic---Dub Techno": 7.917261973489076e-05,
    "Electronic---Dubstep": 0.004889346193522215,
    "Electronic---Dungeon Synth": 1.0428423458108682e-08,
    "Electronic---EBM": 0.0006598730687983334,
    "Electronic---Electro": 0.007644570432603359,
    "Electronic---Electro House": 0.0012926175259053707,
    "Electronic---Electroclash": 8.019379311008379e-05,
    "Electronic---Euro House": 0.0004759978037327528,
    "Electronic---Euro-Disco": 8.014314516913146e-06,
    "Electronic---Eurobeat": 0.00020787116955034435,
    "Electronic---Eurodance": 7.141395326470956e-05,
    "Electronic---Experimental": 0.003298227908089757,
    "Electronic---Freestyle": 0.0003097237495239824,
    "Electronic---Future Jazz": 0.00032893047318793833,
    "Electronic---Gabber": 8.931006959755905e-06,
    "Electronic---Garage House": 0.0004402762860991061,
    "Electronic---Ghetto": 6.767635204596445e-05,
    "Electronic---Ghetto House": 2.1276482584653422e-05,
    "Electronic---Glitch": 0.0009286479325965047,
    "Electronic---Goa Trance": 3.0098744900897145e-06,
    "Electronic---Grime": 0.002125814789906144,
    "Electronic---Halftime": 0.0004921453655697405,
    "Electronic---Hands Up": 0.0001562990219099447,
    "Electronic---Happy Hardcore": 7.1622926043346524e-06,
    "Electronic---Hard House": 2.2997319319983944e-05,
    "Electronic---Hard Techno": 3.507419705783832e-06,
    "Electronic---Hard Trance": 0.00016048143152147532,
    "Electronic---Hardcore": 1.4021014067111537e-05,
    "Electronic---Hardstyle": 3.533498602337204e-05,
    "Electronic---Hi NRG": 7.900333912402857e-06,
    "Electronic---Hip Hop": 0.004952528048306704,
    "Electronic---Hip-House": 0.0011796586913987994,
    "Electronic---House": 0.014209124259650707,
    "Electronic---IDM": 0.00028158113127574325,
    "Electronic---Illbient": 1.5751220416859724e-05,
    "Electronic---Industrial": 0.00025481299962848425,
    "Electronic---Italo House": 4.797231213160558e-06,
    "Electronic---Italo-Disco": 4.1739881453395355e-06,
    "Electronic---Italodance": 3.3526965125929564e-05,
    "Electronic---Jazzdance": 0.0005253837443888187,
    "Electronic---Juke": 0.00017566265887580812,
    "Electronic---Jumpstyle": 2.9203300073277205e-05,
    "Electronic---Jungle": 0.00010404981003375724,
    "Electronic---Latin": 0.0005499100079759955,
    "Electronic---Leftfield": 0.001324704964645207,
    "Electronic---Makina": 2.8033025500917574e-06,
    "Electronic---Minimal": 1.387827614962589e-05,
    "Electronic---Minimal Techno": 0.0001143446279456839,
    "Electronic---Modern Classical": 3.506319899315713e-06,
    "Electronic---Musique Concr\u00e8te": 2.627833168844518e-07,
    "Electronic---Neofolk": 1.561236786074005e-05,
    "Electronic---New Age": 0.00014514093345496804,
    "Electronic---New Beat": 9.964417404262349e-05,
    "Electronic---New Wave": 6.450962246162817e-05,
    "Electronic---Noise": 3.175261781507288e-06,
    "Electronic---Nu-Disco": 0.00292997807264328,
    "Electronic---Power Electronics": 4.288693617127137e-06,
    "Electronic---Progressive Breaks": 0.00015202020586002618,
    "Electronic---Progressive House": 0.0026023134123533964,
    "Electronic---Progressive Trance": 6.440636934712529e-05,
    "Electronic---Psy-Trance": 1.781821447366383e-05,
    "Electronic---Rhythmic Noise": 1.656531276239548e-05,
    "Electronic---Schranz": 8.206322490877938e-06,
    "Electronic---Sound Collage": 1.933953853949788e-06,
    "Electronic---Speed Garage": 0.0012662539957091212,
    "Electronic---Speedcore": 2.2375277239916613e-06,
    "Electronic---Synth-pop": 0.03372093290090561,
    "Electronic---Synthwave": 0.0003446259943302721,
    "Electronic---Tech House": 0.0001554601767566055,
    "Electronic---Tech Trance": 2.632515133882407e-05,
    "Electronic---Techno": 0.0005494076758623123,
    "Electronic---Trance": 0.00044333518599160016,
    "Electronic---Tribal": 9.339869575342163e-05,
    "Electronic---Tribal House": 0.0004401662154123187,
    "Electronic---Trip Hop": 0.00235129427164793,
    "Electronic---Tropical House": 0.011965671554207802,
    "Electronic---UK Garage": 0.0018408768810331821,
    "Electronic---Vaporwave": 6.140930054243654e-05,
    "Folk, World, & Country---African": 6.36120603303425e-05,
    "Folk, World, & Country---Bluegrass": 2.3272871203516843e-06,
    "Folk, World, & Country---Cajun": 1.688171130664884e-11,
    "Folk, World, & Country---Canzone Napoletana": 1.190265152217762e-06,
    "Folk, World, & Country---Catalan Music": 2.157957723625259e-08,
    "Folk, World, & Country---Celtic": 5.939823040534975e-06,
    "Folk, World, & Country---Country": 4.3475306483742315e-06,
    "Folk, World, & Country---Fado": 1.7483951069152681e-06,
    "Folk, World, & Country---Flamenco": 0.00015690700092818588,
    "Folk, World, & Country---Folk": 0.00012481940211728215,
    "Folk, World, & Country---Gospel": 4.093996267329203e-06,
    "Folk, World, & Country---Highlife": 2.7952146410825662e-06,
    "Folk, World, & Country---Hillbilly": 1.972629393165448e-09,
    "Folk, World, & Country---Hindustani": 2.0486219000304118e-05,
    "Folk, World, & Country---Honky Tonk": 1.6658507320244098e-06,
    "Folk, World, & Country---Indian Classical": 5.1737053581746295e-05,
    "Folk, World, & Country---La\u00efk\u00f3": 5.2206116379238665e-05,
    "Folk, World, & Country---Nordic": 5.136885192769114e-07,
    "Folk, World, & Country---Pacific": 2.245127461719676e-06,
    "Folk, World, & Country---Polka": 6.399829999281792e-07,
    "Folk, World, & Country---Ra\u00ef": 4.993176116840914e-05,
    "Folk, World, & Country---Romani": 1.033900298352819e-05,
    "Folk, World, & Country---Soukous": 6.051823220332153e-06,
    "Folk, World, & Country---S\u00e9ga": 7.238782018248457e-08,
    "Folk, World, & Country---Volksmusik": 5.054199281318006e-09,
    "Folk, World, & Country---Zouk": 1.6462628309454885e-06,
    "Folk, World, & Country---\u00c9ntekhno": 4.763263405038742e-06,
    "Funk / Soul---Afrobeat": 0.000934101699385792,
    "Funk / Soul---Boogie": 0.00014689120871480554,
    "Funk / Soul---Contemporary R&B": 0.12602803111076355,
    "Funk / Soul---Disco": 0.00020328427490312606,
    "Funk / Soul---Free Funk": 6.310480330284918e-06,
    "Funk / Soul---Funk": 0.0012764149578288198,
    "Funk / Soul---Gospel": 2.7676544050336815e-05,
    "Funk / Soul---Neo Soul": 0.046416059136390686,
    "Funk / Soul---New Jack Swing": 0.00028990686405450106,
    "Funk / Soul---P.Funk": 3.413023296161555e-05,
    "Funk / Soul---Psychedelic": 2.850518467312213e-05,
    "Funk / Soul---Rhythm & Blues": 0.016648277640342712,
    "Funk / Soul---Soul": 0.009200122207403183,
    "Funk / Soul---Swingbeat": 7.75885782786645e-05,
    "Funk / Soul---UK Street Soul": 0.008872460573911667,
    "Hip Hop---Bass Music": 0.00035779393510892987,
    "Hip Hop---Boom Bap": 0.0011163090821355581,
    "Hip Hop---Bounce": 0.010085365734994411,
    "Hip Hop---Britcore": 7.023240300441103e-08,
    "Hip Hop---Cloud Rap": 0.030484061688184738,
    "Hip Hop---Conscious": 0.004026348702609539,
    "Hip Hop---Crunk": 0.00018069607904180884,
    "Hip Hop---Cut-up/DJ": 5.930618863203563e-05,
    "Hip Hop---DJ Battle Tool": 5.396802589530125e-05,
    "Hip Hop---Electro": 0.0021729900036007166,
    "Hip Hop---G-Funk": 0.000480552640510723,
    "Hip Hop---Gangsta": 0.0008693208219483495,
    "Hip Hop---Grime": 0.011538672260940075,
    "Hip Hop---Hardcore Hip-Hop": 0.0006589677650481462,
    "Hip Hop---Horrorcore": 0.0006135375588200986,
    "Hip Hop---Instrumental": 0.0010894611477851868,
    "Hip Hop---Jazzy Hip-Hop": 0.0012539499439299107,
    "Hip Hop---Miami Bass": 5.43554597243201e-06,
    "Hip Hop---Pop Rap": 0.005270449444651604,
    "Hip Hop---Ragga HipHop": 0.002738756127655506,
    "Hip Hop---RnB/Swing": 0.025285931304097176,
    "Hip Hop---Screw": 0.000330496346578002,
    "Hip Hop---Thug Rap": 0.0014022645773366094,
    "Hip Hop---Trap": 0.24281710386276245,
    "Hip Hop---Trip Hop": 0.0014546385500580072,
    "Hip Hop---Turntablism": 0.0002827032294590026,
    "Jazz---Afro-Cuban Jazz": 1.238087861565873e-06,
    "Jazz---Afrobeat": 3.633818414527923e-05,
    "Jazz---Avant-garde Jazz": 2.2628757960774237e-06,
    "Jazz---Big Band": 8.35586320135917e-07,
    "Jazz---Bop": 4.4754847294825595e-07,
    "Jazz---Bossa Nova": 4.165832797298208e-05,
    "Jazz---Contemporary Jazz": 1.8080012523569167e-05,
    "Jazz---Cool Jazz": 9.70611745287897e-06,
    "Jazz---Dixieland": 4.482720328269352e-08,
    "Jazz---Easy Listening": 2.0568422769429162e-05,
    "Jazz---Free Improvisation": 5.312905955179303e-07,
    "Jazz---Free Jazz": 1.5841496860957704e-06,
    "Jazz---Fusion": 9.779919491847977e-05,
    "Jazz---Gypsy Jazz": 5.181705091672484e-06,
    "Jazz---Hard Bop": 5.393972060119268e-07,
    "Jazz---Jazz-Funk": 0.0002596095728222281,
    "Jazz---Jazz-Rock": 1.2516488823166583e-06,
    "Jazz---Latin Jazz": 3.776183439185843e-05,
    "Jazz---Modal": 1.2303778021305334e-05,
    "Jazz---Post Bop": 1.7455746501582325e-06,
    "Jazz---Ragtime": 1.0341361544874417e-08,
    "Jazz---Smooth Jazz": 3.635440589278005e-05,
    "Jazz---Soul-Jazz": 0.0004255670355632901,
    "Jazz---Space-Age": 4.0420209188596345e-06,
    "Jazz---Swing": 9.490293450653553e-06,
    "Latin---Afro-Cuban": 2.928361027443316e-05,
    "Latin---Bai\u00e3o": 2.0432333158737492e-08,
    "Latin---Batucada": 1.6650894849590259e-06,
    "Latin---Beguine": 6.893207782354693e-09,
    "Latin---Bolero": 2.1525049305637367e-05,
    "Latin---Boogaloo": 1.3197345651860815e-05,
    "Latin---Bossanova": 0.00010499337804503739,
    "Latin---Cha-Cha": 5.586188763118116e-06,
    "Latin---Charanga": 2.055857706295683e-08,
    "Latin---Compas": 6.599273660867766e-08,
    "Latin---Cubano": 4.156429713475518e-05,
    "Latin---Cumbia": 8.923940185923129e-05,
    "Latin---Descarga": 4.763936885865405e-06,
    "Latin---Forr\u00f3": 1.3574835065810475e-05,
    "Latin---Guaguanc\u00f3": 3.8908336819076794e-07,
    "Latin---Guajira": 6.439220356924125e-08,
    "Latin---Guaracha": 7.218895348160004e-08,
    "Latin---MPB": 4.7486792027484626e-06,
    "Latin---Mambo": 1.548293039377313e-05,
    "Latin---Mariachi": 1.07576079244609e-06,
    "Latin---Merengue": 3.327307422296144e-05,
    "Latin---Norte\u00f1o": 2.3838727429392748e-05,
    "Latin---Nueva Cancion": 2.9297380024218e-06,
    "Latin---Pachanga": 2.0677158317994326e-05,
    "Latin---Porro": 1.5470995151645184e-07,
    "Latin---Ranchera": 2.463018972775899e-06,
    "Latin---Reggaeton": 0.11707116663455963,
    "Latin---Rumba": 5.5625077948207036e-05,
    "Latin---Salsa": 0.00036046613240614533,
    "Latin---Samba": 7.246081622724887e-06,
    "Latin---Son": 2.008714403700651e-07,
    "Latin---Son Montuno": 1.7283844044868601e-07,
    "Latin---Tango": 6.36510958429426e-05,
    "Latin---Tejano": 1.3293514484757907e-06,
    "Latin---Vallenato": 3.511540626277565e-06,
    "Non-Music---Audiobook": 1.58822288653937e-07,
    "Non-Music---Comedy": 4.925204393657623e-06,
    "Non-Music---Dialogue": 5.037187520429143e-07,
    "Non-Music---Education": 2.2895471829542657e-06,
    "Non-Music---Field Recording": 1.351967512164265e-06,
    "Non-Music---Interview": 1.7961201592697762e-05,
    "Non-Music---Monolog": 1.7101143612308078e-07,
    "Non-Music---Poetry": 1.721102194096602e-06,
    "Non-Music---Political": 7.378916393463442e-07,
    "Non-Music---Promotional": 2.5752112264854077e-07,
    "Non-Music---Radioplay": 3.7408184994092153e-07,
    "Non-Music---Religious": 2.9126813387847506e-06,
    "Non-Music---Spoken Word": 4.244042884238297e-06,
    "Pop---Ballad": 0.003262103069573641,
    "Pop---Bollywood": 1.7584714441909455e-05,
    "Pop---Bubblegum": 0.008070488460361958,
    "Pop---Chanson": 0.00013437790039461106,
    "Pop---City Pop": 0.0008694206480868161,
    "Pop---Europop": 0.0023066624999046326,
    "Pop---Indie Pop": 0.01118538435548544,
    "Pop---J-pop": 0.0010393609991297126,
    "Pop---K-pop": 0.04089515283703804,
    "Pop---Kay\u014dkyoku": 2.2085002910898766e-06,
    "Pop---Light Music": 0.0006102723418734968,
    "Pop---Music Hall": 5.742260213992267e-07,
    "Pop---Novelty": 0.00010165132698602974,
    "Pop---Parody": 5.145810791873373e-05,
    "Pop---Schlager": 8.791564596322132e-07,
    "Pop---Vocal": 0.012524578720331192,
    "Reggae---Calypso": 1.5567027276119916e-06,
    "Reggae---Dancehall": 0.0008000099915079772,
    "Reggae---Dub": 9.778740059118718e-05,
    "Reggae---Lovers Rock": 3.372884020791389e-05,
    "Reggae---Ragga": 0.00010628750897012651,
    "Reggae---Reggae": 0.0002934916701633483,
    "Reggae---Reggae-Pop": 0.00121020816732198,
    "Reggae---Rocksteady": 1.983549282158492e-06,
    "Reggae---Roots Reggae": 3.713578553288244e-05,
    "Reggae---Ska": 8.161095479408687e-07,
    "Reggae---Soca": 6.740850722053437e-07,
    "Rock---AOR": 2.4198767277994193e-05,
    "Rock---Acid Rock": 1.4963584362703841e-06,
    "Rock---Acoustic": 3.3406224247301e-05,
    "Rock---Alternative Rock": 0.0013484113151207566,
    "Rock---Arena Rock": 1.095484321922413e-06,
    "Rock---Art Rock": 1.851819069997873e-05,
    "Rock---Atmospheric Black Metal": 1.3395097084867302e-06,
    "Rock---Avantgarde": 4.119794084544992e-06,
    "Rock---Beat": 2.818409939209232e-06,
    "Rock---Black Metal": 3.84986788048991e-06,
    "Rock---Blues Rock": 2.46787249125191e-06,
    "Rock---Brit Pop": 8.072573837125674e-05,
    "Rock---Classic Rock": 4.6904182227081037e-07,
    "Rock---Coldwave": 2.567454657764756e-06,
    "Rock---Country Rock": 1.9315482404635986e-06,
    "Rock---Crust": 2.382280861468189e-08,
    "Rock---Death Metal": 6.847765689599328e-06,
    "Rock---Deathcore": 9.31921476876596e-06,
    "Rock---Deathrock": 5.012219617128721e-07,
    "Rock---Depressive Black Metal": 7.619342454745492e-07,
    "Rock---Doo Wop": 1.2109557019357453e-06,
    "Rock---Doom Metal": 1.0846362101801788e-06,
    "Rock---Dream Pop": 1.6136767953867093e-05,
    "Rock---Emo": 0.00018179151811636984,
    "Rock---Ethereal": 6.387108442140743e-05,
    "Rock---Experimental": 1.3859032151231077e-05,
    "Rock---Folk Metal": 1.5501359484915156e-06,
    "Rock---Folk Rock": 8.592533959017601e-06,
    "Rock---Funeral Doom Metal": 6.9570057803503e-07,
    "Rock---Funk Metal": 2.0266548972358578e-07,
    "Rock---Garage Rock": 2.7946741738560377e-06,
    "Rock---Glam": 2.283061121488572e-06,
    "Rock---Goregrind": 1.0636385994189368e-08,
    "Rock---Goth Rock": 3.6667577205662383e-06,
    "Rock---Gothic Metal": 2.3021580091153737e-06,
    "Rock---Grindcore": 1.3176775155443465e-06,
    "Rock---Grunge": 1.569786218169611e-05,
    "Rock---Hard Rock": 1.7416573427908588e-06,
    "Rock---Hardcore": 6.871272489661351e-06,
    "Rock---Heavy Metal": 1.0418515557830688e-05,
    "Rock---Indie Rock": 0.0003451387456152588,
    "Rock---Industrial": 3.2801690394990146e-06,
    "Rock---Krautrock": 1.5602014400428743e-06,
    "Rock---Lo-Fi": 1.7942649719770998e-05,
    "Rock---Lounge": 0.00011181634181411937,
    "Rock---Math Rock": 2.2895706024428364e-06,
    "Rock---Melodic Death Metal": 2.7203325316804694e-06,
    "Rock---Melodic Hardcore": 5.282788151816931e-06,
    "Rock---Metalcore": 1.243841052200878e-05,
    "Rock---Mod": 1.0589911880742875e-06,
    "Rock---Neofolk": 3.6850678952760063e-06,
    "Rock---New Wave": 2.7961521482211538e-05,
    "Rock---No Wave": 4.98181134389597e-06,
    "Rock---Noise": 1.226456731728831e-07,
    "Rock---Noisecore": 7.874866092549837e-09,
    "Rock---Nu Metal": 7.08961597410962e-05,
    "Rock---Oi": 2.8837316534691126e-08,
    "Rock---Parody": 7.039290267130127e-06,
    "Rock---Pop Punk": 2.6723721020971425e-05,
    "Rock---Pop Rock": 0.0006048707873560488,
    "Rock---Pornogrind": 6.041216238372726e-08,
    "Rock---Post Rock": 1.810282469705271e-06,
    "Rock---Post-Hardcore": 1.2858994523412548e-05,
    "Rock---Post-Metal": 1.9708878085111792e-07,
    "Rock---Post-Punk": 7.3944966061390005e-06,
    "Rock---Power Metal": 5.940929099779169e-07,
    "Rock---Power Pop": 2.5290266421507113e-05,
    "Rock---Power Violence": 1.0475985590119308e-07,
    "Rock---Prog Rock": 5.20240746482159e-06,
    "Rock---Progressive Metal": 3.426626733471494e-07,
    "Rock---Psychedelic Rock": 7.212263153633103e-05,
    "Rock---Psychobilly": 1.0183829317611526e-06,
    "Rock---Pub Rock": 3.2201634780903987e-07,
    "Rock---Punk": 5.188422801438719e-05,
    "Rock---Rock & Roll": 6.275040959735634e-06,
    "Rock---Rockabilly": 1.4315905616513191e-07,
    "Rock---Shoegaze": 7.218778591777664e-06,
    "Rock---Ska": 6.149087425910693e-07,
    "Rock---Sludge Metal": 5.805619096577175e-08,
    "Rock---Soft Rock": 2.6570600311970338e-05,
    "Rock---Southern Rock": 2.5716727236613224e-07,
    "Rock---Space Rock": 6.039968411641894e-06,
    "Rock---Speed Metal": 2.0616714380139456e-07,
    "Rock---Stoner Rock": 1.1501889503051643e-06,
    "Rock---Surf": 3.8019113617338007e-06,
    "Rock---Symphonic Rock": 1.9402068573981524e-06,
    "Rock---Technical Death Metal": 1.3259669628951087e-07,
    "Rock---Thrash": 5.358567136681813e-07,
    "Rock---Twist": 3.796566616642849e-08,
    "Rock---Viking Metal": 2.1567391286225757e-06,
    "Rock---Y\u00e9-Y\u00e9": 2.0144817369782686e-07,
    "Stage & Screen---Musical": 2.108983062498737e-05,
    "Stage & Screen---Score": 2.1411067791632377e-05,
    "Stage & Screen---Soundtrack": 0.0004993847105652094,
    "Stage & Screen---Theme": 2.3946642613736913e-05
  },
  "discogs_embedding_mean": [
    0.019247038289904594,
    -0.0030389537569135427,
    -0.02100774459540844,
    0.1707421988248825,
    -0.01540231890976429,
    0.05290830880403519,
    0.24833552539348602,
    0.13127997517585754,
    -0.005159204825758934,
    -0.0004926882102154195,
    0.6134771108627319,
    -0.022670965641736984,
    0.07206760346889496,
    0.030153639614582062,
    -0.015721607953310013,
    0.13290242850780487,
    0.05261189490556717,
    0.04443821310997009,
    0.22521398961544037,
    0.012323512695729733,
    0.036662787199020386,
    0.010913082398474216,
    0.03052314557135105,
    0.025758743286132812,
    0.05793435871601105,
    -0.00010225754522252828,
    0.007379683665931225,
    -0.027955396100878716,
    0.04261629283428192,
    -0.01736338622868061,
    -0.03145976364612579,
    0.025132035836577415,
    -0.007993750274181366,
    -0.006292616482824087,
    0.2479441910982132,
    0.1504388451576233,
    -0.002614970551803708,
    -0.04679078608751297,
    -0.045357488095760345,
    0.10962926596403122,
    0.05943514034152031,
    -0.06689589470624924,
    -0.020424742251634598,
    0.427467942237854,
    0.06101192161440849,
    0.1936570703983307,
    -0.04666893184185028,
    0.11912067234516144,
    0.0035850326530635357,
    0.15708202123641968,
    -0.01953199878334999,
    -0.07253046333789825,
    -0.010686852969229221,
    0.1960781365633011,
    -0.012746051885187626,
    0.14659053087234497,
    0.08013898879289627,
    -0.011936377733945847,
    0.010296202264726162,
    -0.07615746557712555,
    -0.0037952265702188015,
    0.08218835294246674,
    -0.03834698349237442,
    -0.03780928626656532,
    0.013293512165546417,
    -0.0056038242764770985,
    0.06217384710907936,
    -0.06775547564029694,
    -0.030579961836338043,
    -0.048221174627542496,
    0.029068244621157646,
    0.003307688282802701,
    0.012841894291341305,
    0.010870597325265408,
    -0.014452951028943062,
    0.47038987278938293,
    0.07177828252315521,
    -0.01019915658980608,
    -0.026465144008398056,
    0.09952068328857422,
    -0.06448699533939362,
    0.012733501382172108,
    -0.06152801960706711,
    0.15235218405723572,
    -0.011652924120426178,
    0.004726450424641371,
    0.2808099687099457,
    -0.06718336790800095,
    -0.0036764570977538824,
    0.7300267815589905,
    0.12045740336179733,
    0.057007722556591034,
    -0.01560202520340681,
    0.0457850806415081,
    -0.027331527322530746,
    -0.033911775797605515,
    0.13391853868961334,
    -0.007485447451472282,
    0.42119985818862915,
    0.07416778057813644,
    0.169748917222023,
    -0.04953061044216156,
    0.02380312606692314,
    -0.024200720712542534,
    0.0393219068646431,
    0.5346155762672424,
    -0.06904612481594086,
    -0.013740293681621552,
    -0.0018712831661105156,
    -0.05697029456496239,
    0.12683527171611786,
    0.026480495929718018,
    0.03386417776346207,
    -0.02713759057223797,
    0.5578941106796265,
    -0.013401289470493793,
    0.2633092701435089,
    -0.06716852635145187,
    0.26814332604408264,
    -0.0076480768620967865,
    0.09069588780403137,
    0.06447780132293701,
    -0.0005309805274009705,
    -0.026285307481884956,
    0.010599824599921703,
    -0.042471252381801605,
    0.24696163833141327,
    0.009196801111102104,
    -0.021177921444177628,
    -0.01948700286448002,
    0.0676318109035492,
    0.061740580946207047,
    0.17131395637989044,
    -0.06091918796300888,
    0.01760999485850334,
    0.12590649724006653,
    0.05993076413869858,
    1.9559958673198707e-05,
    0.17907094955444336,
    -0.017315369099378586,
    0.009371696971356869,
    -0.015231519006192684,
    -0.04081770405173302,
    -0.033356279134750366,
    -0.019185245037078857,
    0.0018328047590330243,
    0.15962740778923035,
    -0.061058543622493744,
    -0.007637667469680309,
    0.05466071516275406,
    0.2334488481283188,
    -0.007768833544105291,
    0.07118246704339981,
    0.44727471470832825,
    0.0083582429215312,
    -0.036933429539203644,
    -0.035305965691804886,
    -0.016743026673793793,
    0.07664395123720169,
    0.10768784582614899,
    0.1511920541524887,
    0.029232142493128777,
    0.06749726086854935,
    0.036776550114154816,
    0.013586549088358879,
    0.24348853528499603,
    0.03726072981953621,
    0.037463024258613586,
    0.11389085650444031,
    0.12347573041915894,
    0.05910884961485863,
    0.0391620434820652,
    0.053240980952978134,
    0.03369602560997009,
    0.018966587260365486,
    -0.06494922935962677,
    0.018490461632609367,
    0.05353233590722084,
    -0.02904353104531765,
    0.047866515815258026,
    0.3851972222328186,
    0.13736386597156525,
    0.057696469128131866,
    0.02580811269581318,
    0.1465948224067688,
    0.044127773493528366,
    0.07281343638896942,
    -0.0750686526298523,
    0.032261382788419724,
    -0.04063906893134117,
    0.0693708136677742,
    0.011382345110177994,
    0.0664261132478714,
    0.06728736311197281,
    -0.054212745279073715,
    -0.01136562880128622,
    0.03956754505634308,
    0.14624135196208954,
    0.004888593684881926,
    0.02969239465892315,
    0.008894959464669228,
    -0.0033766154665499926,
    -0.029466286301612854,
    0.0054624928161501884,
    0.005473563447594643,
    -0.026693236082792282,
    0.08414646983146667,
    0.35059571266174316,
    0.030220521613955498,
    0.06090286374092102,
    0.0023983523715287447,
    -0.018090566620230675,
    0.09222324937582016,
    -0.015289576724171638,
    0.005304153077304363,
    0.02992207184433937,
    -0.005710334051400423,
    -0.02993575669825077,
    -0.0008658775477670133,
    0.02478877268731594,
    0.25133734941482544,
    -0.05085841938853264,
    0.030795162543654442,
    0.6506757140159607,
    0.007393664680421352,
    -0.016858095303177834,
    0.3567250072956085,
    0.01101662777364254,
    -0.026923397555947304,
    0.06303197890520096,
    -0.031430408358573914,
    -0.02911566197872162,
    -0.04605131596326828,
    -0.07443289458751678,
    0.08226457983255386,
    0.0008605862385593355,
    0.00868033617734909,
    0.27826470136642456,
    0.041048549115657806,
    -0.018857581540942192,
    -0.005163857713341713,
    0.06461001187562943,
    0.0921202152967453,
    -0.04180801287293434,
    0.04835866764187813,
    -0.01690453477203846,
    -0.06681960821151733,
    -0.037364453077316284,
    0.0743924081325531,
    0.08587512373924255,
    -0.030657654628157616,
    -0.037565503269433975,
    0.036482468247413635,
    0.025778602808713913,
    0.48311784863471985,
    0.03002222813665867,
    -0.06470433622598648,
    0.08664558827877045,
    0.08914728462696075,
    -0.09431686252355576,
    0.15065044164657593,
    -0.065597303211689,
    0.03637097030878067,
    0.08732093125581741,
    0.04478970915079117,
    0.021516792476177216,
    -0.0012626901734620333,
    0.4593825042247772,
    0.1182146742939949,
    0.0054906560108065605,
    -0.08568119257688522,
    0.020866990089416504,
    -0.03370986878871918,
    -0.04995846003293991,
    0.0012660841457545757,
    0.06557967513799667,
    0.1276988685131073,
    0.07556849718093872,
    -0.019092507660388947,
    -0.044101305305957794,
    -0.004202965181320906,
    0.1866205483675003,
    -0.0032104304991662502,
    0.022381026297807693,
    0.0016902773641049862,
    0.06647138297557831,
    0.04572681710124016,
    0.06316067278385162,
    0.14892815053462982,
    -0.0006023335736244917,
    -0.034078676253557205,
    -0.04466324672102928,
    0.03398754447698593,
    0.03651588037610054,
    0.054214801639318466,
    0.03444133326411247,
    0.06266278773546219,
    0.05501559376716614,
    0.5811413526535034,
    -0.023144857957959175,
    0.07218804955482483,
    0.16043922305107117,
    0.679771900177002,
    -0.03499150648713112,
    0.004955966491252184,
    0.05785086005926132,
    0.5698502063751221,
    0.017608340829610825,
    -0.05020802095532417,
    0.24369564652442932,
    0.09195560961961746,
    0.002824304159730673,
    0.02841116674244404,
    0.01086094044148922,
    -0.0576765201985836,
    -0.028073780238628387,
    -0.04830911383032799,
    -0.024377766996622086,
    -0.017384232953190804,
    -0.022839156910777092,
    -0.023256435990333557,
    0.03119669295847416,
    0.01508724968880415,
    -0.0006719218799844384,
    0.23843953013420105,
    0.4299546182155609,
    -0.02606421895325184,
    0.06102598458528519,
    0.6449989080429077,
    0.05645099654793739,
    0.011341548524796963,
    -0.002589404582977295,
    -0.016695700585842133,
    -0.05499736964702606,
    0.07495708018541336,
    0.188463494181633,
    -0.023393623530864716,
    -0.010258397087454796,
    -0.049953434616327286,
    0.1390102654695511,
    0.06286204606294632,
    -0.032384902238845825,
    0.06876401603221893,
    0.1434677094221115,
    -0.028864499181509018,
    0.07232427597045898,
    -0.0025496366433799267,
    0.2796052098274231,
    0.08322359621524811,
    0.08643544465303421,
    -0.015743691474199295,
    -0.05054503306746483,
    -0.04551800712943077,
    0.05142565816640854,
    0.2059115469455719,
    0.044138409197330475,
    -0.011544712819159031,
    0.009475580416619778,
    0.14553867280483246,
    0.025423722341656685,
    -0.04251501336693764,
    0.09306042641401291,
    0.013305635191500187,
    0.04687326401472092,
    0.0528501495718956,
    -0.007414731662720442,
    0.00026365838130004704,
    0.052147816866636276,
    -0.021310102194547653,
    0.0694611594080925,
    0.4759391248226166,
    -0.044894348829984665,
    0.07229269295930862,
    -0.01709028333425522,
    -0.016965540125966072,
    0.27976614236831665,
    0.08746149390935898,
    0.01935867965221405,
    0.400910347700119,
    0.024379627779126167,
    -0.009426089003682137,
    -0.04254329204559326,
    0.018379153683781624,
    0.10404101759195328,
    0.11720428615808487,
    0.2194475680589676,
    0.01687277853488922,
    -0.002882544184103608,
    0.20811447501182556,
    -0.02687341533601284,
    -0.00987810455262661,
    0.0037484713830053806,
    -0.019635437056422234,
    -0.01371245738118887,
    -0.01636296883225441,
    0.02482348121702671,
    -0.00761815020814538,
    -0.04348580539226532,
    -0.016010452061891556,
    -0.00022439022723119706,
    -0.049434058368206024,
    0.05535423755645752,
    0.06321372836828232,
    0.07483070343732834,
    0.035038258880376816,
    0.04740355908870697,
    -0.056795358657836914,
    0.06582816690206528,
    -0.023089956492185593,
    -0.01873638667166233,
    0.10708091408014297,
    0.013204289600253105,
    0.08947516232728958,
    -0.03536485880613327,
    -0.060217153280973434,
    -0.05929160118103027,
    -0.0076818629167973995,
    0.028774047270417213,
    0.03585146740078926,
    0.003714142832905054,
    -0.005016402341425419,
    0.02968035824596882,
    0.06189173832535744,
    -0.010671072639524937,
    -0.03345661610364914,
    0.03390444815158844,
    0.10892839729785919,
    0.0831056460738182,
    -0.05774708837270737,
    -0.06306599825620651,
    -0.006777399685233831,
    -0.058308593928813934,
    -0.016333457082509995,
    0.12207303941249847,
    -0.011905300430953503,
    -0.01990763284265995,
    -0.05163042992353439,
    0.01188062597066164,
    0.608601987361908,
    -0.05026179179549217,
    -0.02202911674976349,
    0.11367367208003998,
    -0.009516444988548756,
    0.03696974366903305,
    0.25142917037010193,
    -0.03149016201496124,
    0.038688067346811295,
    0.14148198068141937,
    0.09267101436853409,
    -0.05484030395746231,
    -0.055672869086265564,
    0.19636087119579315,
    0.01309655699878931,
    0.022276422008872032,
    0.003092180471867323,
    0.008219143375754356,
    0.03487516567111015,
    -0.06939186155796051,
    -0.012259019538760185,
    -0.06959924846887589,
    -0.034158386290073395,
    0.04600686952471733,
    0.018749261274933815,
    0.24072249233722687,
    -0.0552213080227375,
    0.03510785102844238,
    -0.01629890874028206,
    0.18445631861686707,
    -0.04001679643988609,
    0.1295165717601776,
    0.18529145419597626,
    0.01899885945022106,
    0.09345753490924835,
    0.02407335862517357,
    0.7189882397651672,
    0.004240343347191811,
    -0.033429548144340515,
    0.4863423705101013,
    0.056059930473566055,
    0.030677733942866325,
    0.2616308927536011,
    0.04200666770339012,
    -0.0022514162119477987,
    0.024249181151390076,
    0.36924779415130615,
    0.5426714420318604,
    0.05767010897397995,
    0.07898145914077759,
    -0.00910514872521162,
    0.014245603233575821,
    -0.03245748206973076,
    -0.03222815692424774,
    -0.07603905349969864,
    -0.001961970468983054,
    0.05583906173706055,
    0.09399212151765823,
    0.026398422196507454,
    -0.04100938141345978,
    -0.01548323966562748,
    0.025360481813549995,
    0.023883329704403877,
    0.22512072324752808,
    0.05537475273013115,
    0.4016408324241638,
    0.030179234221577644,
    -0.02297363057732582,
    0.030724061653017998,
    0.006464135833084583,
    0.022242724895477295,
    0.06806446611881256,
    -0.0391431488096714,
    -0.04480187967419624,
    0.043210700154304504,
    0.04273555427789688,
    0.03914951905608177,
    0.01392899826169014,
    0.017793899402022362,
    0.05113480985164642,
    -0.00867177452892065,
    0.15363581478595734,
    0.2715291380882263,
    0.07524513453245163,
    -0.026290006935596466,
    0.0918564572930336,
    0.6778366565704346,
    0.001934219035319984,
    0.03865748271346092,
    -0.017099730670452118,
    0.045032184571027756,
    -0.06405694782733917,
    -0.060529932379722595,
    -0.014098607935011387,
    0.30472129583358765,
    0.03187534213066101,
    -0.007331068627536297,
    -0.06234554201364517,
    0.15380316972732544,
    0.05833950266242027,
    -0.07197423279285431,
    0.26017722487449646,
    0.018021181225776672,
    0.07703763246536255,
    0.036571040749549866,
    -0.03732474893331528,
    -0.054007723927497864,
    -0.009084722027182579,
    0.0017830281285569072,
    -0.0517226867377758,
    0.022773059085011482,
    0.05924296751618385,
    0.00377872446551919,
    0.03173018991947174,
    0.09327591210603714,
    -0.0230758935213089,
    -0.06295472383499146,
    -0.0026003774255514145,
    -0.018476352095603943,
    -0.037253912538290024,
    0.038846638053655624,
    0.03933132067322731,
    -0.047232501208782196,
    0.14790721237659454,
    -0.009005853906273842,
    0.03502209484577179,
    0.05640125647187233,
    -0.0070183235220611095,
    0.11842963844537735,
    0.052856236696243286,
    0.005071306601166725,
    0.0171116441488266,
    -0.07140196859836578,
    -0.03523891791701317,
    -0.05234546586871147,
    -0.009246490895748138,
    -0.01794799230992794,
    0.03932412713766098,
    -0.022815370932221413,
    0.006550518795847893,
    0.08405288308858871,
    0.08081390708684921,
    -0.0695343166589737,
    0.09906449168920517,
    0.015554421581327915,
    0.33674728870391846,
    0.012601503171026707,
    -0.017345428466796875,
    -0.019950293004512787,
    0.00010555828339420259,
    0.0777164101600647,
    0.10101181268692017,
    -0.012454729527235031,
    -0.02212348021566868,
    0.1147906482219696,
    -0.02204490825533867,
    0.061497561633586884,
    0.017758809030056,
    -0.023775113746523857,
    0.04755442216992378,
    -0.028063282370567322,
    -0.039815571159124374,
    0.030980076640844345,
    -0.011665211990475655,
    0.0031842889729887247,
    0.01476656086742878,
    -0.020609449595212936,
    -0.004776493646204472,
    0.39210349321365356,
    0.11209787428379059,
    0.013721566647291183,
    0.2211475968360901,
    0.011314094066619873,
    0.11938827484846115,
    0.03621659427881241,
    0.016499947756528854,
    0.06973350793123245,
    -0.032155465334653854,
    -0.022809907793998718,
    -0.01975385844707489,
    -0.02588813193142414,
    0.013734697364270687,
    0.020356005057692528,
    0.11504960805177689,
    -0.04085038602352142,
    -0.013047087006270885,
    0.0733957439661026,
    0.06171897426247597,
    -0.06760960817337036,
    0.09802255779504776,
    0.40620899200439453,
    -0.0005322280339896679,
    -0.011842341162264347,
    -0.016110742464661598,
    0.10279048979282379,
    -0.04841890558600426,
    0.005128449760377407,
    -0.059247322380542755,
    0.014796102419495583,
    0.049531273543834686,
    -0.05228224769234657,
    0.1781863570213318,
    -0.001228407258167863,
    -0.044791337102651596,
    -0.026354633271694183,
    0.07538972795009613,
    0.03542880713939667,
    -0.037850189954042435,
    0.023512283340096474,
    -0.07485045492649078,
    0.17288212478160858,
    0.00696105370298028,
    0.1887866109609604,
    -0.025219276547431946,
    0.11803869903087616,
    0.36198127269744873,
    0.03546922281384468,
    0.07471689581871033,
    0.02390783466398716,
    0.20465122163295746,
    0.0910651907324791,
    0.00862758606672287,
    0.13080216944217682,
    0.10528159886598587,
    -0.060204703360795975,
    -0.05369284749031067,
    0.004554715473204851,
    0.02438214048743248,
    0.13557496666908264,
    0.11207252740859985,
    -0.0034396664705127478,
    -0.05783307924866676,
    0.17176450788974762,
    0.14077001810073853,
    -0.05250830948352814,
    0.06109381839632988,
    -0.048210304230451584,
    0.015815969556570053,
    0.0520968995988369,
    0.0418032705783844,
    -0.00874672457575798,
    0.013967892155051231,
    -0.07335366308689117,
    -0.028696462512016296,
    0.08917268365621567,
    -0.01754804514348507,
    0.04469871148467064,
    -0.014423239976167679,
    0.03864877298474312,
    -0.030433494597673416,
    0.03845570236444473,
    0.054612595587968826,
    -0.04228142648935318,
    0.018706489354372025,
    0.28584662079811096,
    -0.055309686809778214,
    -0.0018702285597100854,
    -0.04737280681729317,
    -0.022409701719880104,
    0.044824548065662384,
    -0.008777951821684837,
    0.7352694869041443,
    0.08884056657552719,
    0.02714206650853157,
    0.05652260407805443,
    0.22892560064792633,
    -0.06516800820827484,
    0.028888383880257607,
    -0.03481946885585785,
    -0.034710779786109924,
    -0.03434149920940399,
    0.002434887457638979,
    -0.02182748354971409,
    -0.010810782201588154,
    -0.02882976457476616,
    -0.03000318631529808,
    0.038374163210392,
    -0.0027502793818712234,
    0.005126255564391613,
    -0.006631497293710709,
    0.058224186301231384,
    0.03279009833931923,
    0.09202075004577637,
    0.012983626686036587,
    0.02474939450621605,
    0.048370204865932465,
    0.0887162983417511,
    0.0075478204526007175,
    0.07600370794534683,
    -0.034311458468437195,
    0.00440368102863431,
    0.34384885430336,
    -0.041796837002038956,
    0.16788512468338013,
    0.15702539682388306,
    -0.05294802784919739,
    -0.04372428357601166,
    -0.03559664264321327,
    -0.030647916719317436,
    0.540651261806488,
    0.03704819083213806,
    -0.032454963773489,
    0.030515117570757866,
    -0.0012209952110424638,
    -0.013971388339996338,
    0.24898192286491394,
    0.025314800441265106,
    -0.012606517411768436,
    -0.009353169240057468,
    -0.046906210482120514,
    -0.04532439261674881,
    -0.05822106823325157,
    0.021206378936767578,
    -0.029838521033525467,
    0.04587850719690323,
    -0.06277664005756378,
    -0.014102987945079803,
    -0.01575247012078762,
    0.1236630231142044,
    0.01920107565820217,
    0.09539420157670975,
    -0.008666446432471275,
    0.01927291601896286,
    0.11169597506523132,
    0.19944985210895538,
    0.02223082445561886,
    0.07242130488157272,
    0.012492204084992409,
    -0.029607975855469704,
    -0.01461619883775711,
    0.04108429327607155,
    0.05069097504019737,
    0.032659582793712616,
    0.025704041123390198,
    0.07357673346996307,
    -0.004651769530028105,
    0.11631744354963303,
    0.08543000370264053,
    0.04658275097608566,
    0.05373922362923622,
    0.039904117584228516,
    0.022739512845873833,
    -0.008987238630652428,
    0.19267277419567108,
    0.033553313463926315,
    0.05167097970843315,
    0.02152419090270996,
    0.10031260550022125,
    -0.011623515747487545,
    -0.024196771904826164,
    -0.05147607997059822,
    -0.06676982343196869,
    -0.014711561612784863,
    0.0844736248254776,
    0.04031403362751007,
    0.010227276012301445,
    0.028698312118649483,
    0.1984875649213791,
    0.3655282258987427,
    -0.013532916083931923,
    0.033870767802000046,
    0.019557800143957138,
    0.002696934388950467,
    -0.04305922985076904,
    -0.007930032908916473,
    0.2152954339981079,
    0.031549323350191116,
    0.01155197061598301,
    0.017831791192293167,
    -0.011337436735630035,
    0.43961313366889954,
    0.0315907783806324,
    0.08793872594833374,
    0.08392471820116043,
    0.019591443240642548,
    0.050993017852306366,
    0.0008362117223441601,
    -0.001644930918700993,
    0.010314351879060268,
    -0.0063612498342990875,
    0.12404234707355499,
    0.26558902859687805,
    0.3408006429672241,
    -0.010015690699219704,
    0.03603097051382065,
    0.03366010636091232,
    -0.03214350342750549,
    -0.005741222761571407,
    0.02639206498861313,
    0.03189947456121445,
    0.0099337138235569,
    -0.0031463897321373224,
    -0.03900028020143509,
    0.08166614174842834,
    0.014359635300934315,
    0.012771574780344963,
    0.20175212621688843,
    -0.03152972087264061,
    0.3083231747150421,
    0.010638720355927944,
    0.2421606034040451,
    -0.02470047026872635,
    -0.010157131589949131,
    0.0760510265827179,
    -0.02128208987414837,
    0.007967863231897354,
    0.06952442228794098,
    -0.08390587568283081,
    0.010098347440361977,
    0.03679080680012703,
    -0.037467628717422485,
    0.017778487876057625,
    0.06365737318992615,
    0.2695934474468231,
    0.24666649103164673,
    0.7871391177177429,
    0.12547674775123596,
    -0.005846956744790077,
    0.025786783546209335,
    0.013794214464724064,
    0.006214250810444355,
    0.11015018075704575,
    -0.005613312590867281,
    0.02756440080702305,
    -0.002709099557250738,
    -0.0169081911444664,
    0.12704363465309143,
    0.03043648786842823,
    0.055494360625743866,
    -0.034423474222421646,
    0.09078207612037659,
    -0.010742447338998318,
    -0.03478166088461876,
    -0.017127493396401405,
    0.03890828415751457,
    0.046559110283851624,
    -0.045356396585702896,
    -0.008957514539361,
    0.016882579773664474,
    -0.05013562738895416,
    0.008417892269790173,
    0.12178900092840195,
    -0.008126498199999332,
    0.3977263569831848,
    0.06690666079521179,
    0.25400233268737793,
    -0.05402712896466255,
    -0.015646664425730705,
    -0.004571801517158747,
    0.02275286801159382,
    -0.005654191132634878,
    -0.0030079877469688654,
    0.47470948100090027,
    0.1183122768998146,
    -0.047445353120565414,
    0.13075897097587585,
    -0.010356420651078224,
    0.05822280794382095,
    0.047172535210847855,
    -0.032250333577394485,
    -0.004308087285608053,
    -0.02923957072198391,
    -0.0455293133854866,
    0.015769828110933304,
    0.00779571570456028,
    0.05369943752884865,
    0.1021978110074997,
    0.03129737824201584,
    0.10301923751831055,
    -0.0024730192963033915,
    -0.019638944417238235,
    0.020777758210897446,
    -0.05429408326745033,
    0.003091598628088832,
    0.03494948893785477,
    0.007014882750809193,
    0.01107999961823225,
    0.0032464489340782166,
    0.0011612868402153254,
    0.22182367742061615,
    -0.05178794637322426,
    0.00459224684163928,
    -0.02896568737924099,
    -0.07114724814891815,
    0.27089449763298035,
    -0.01681128516793251,
    -0.002966402331367135,
    0.11955326050519943,
    0.02383788675069809,
    0.1921171098947525,
    0.009594710543751717,
    -0.007130775600671768,
    -0.04134216904640198,
    -0.03623483330011368,
    0.018575619906187057,
    0.1996874362230301,
    0.11803105473518372,
    0.17162726819515228,
    -0.03461497649550438,
    0.02298757992684841,
    0.09820728749036789,
    0.37521761655807495,
    -0.004779345355927944,
    -0.01877138949930668,
    0.052365295588970184,
    0.033832401037216187,
    0.6889510154724121,
    0.013908474706113338,
    0.16888797283172607,
    0.21581484377384186,
    0.1310204118490219,
    -0.07242261618375778,
    -0.01518477313220501,
    0.48551496863365173,
    -0.06648551672697067,
    0.04053233563899994,
    0.11970463395118713,
    0.46602192521095276,
    0.01969698816537857,
    0.15814654529094696,
    -0.025818251073360443,
    0.032975662499666214,
    0.3533211052417755,
    -0.047498732805252075,
    0.0607704222202301,
    -0.013506597839295864,
    0.04115920141339302,
    0.008965011686086655,
    0.026502810418605804,
    0.01256865169852972,
    0.088731549680233,
    -0.03926105797290802,
    0.018688201904296875,
    0.21043561398983002,
    0.169068843126297,
    0.07673269510269165,
    0.40785130858421326,
    0.05637660622596741,
    0.008902112953364849,
    0.036349955946207047,
    0.0070225694216787815,
    0.15668898820877075,
    0.0519743375480175,
    0.011984644457697868,
    0.10685958713293076,
    0.03350880369544029,
    0.04523319751024246,
    -0.010444823652505875,
    -0.02991320565342903,
    0.049582697451114655,
    -0.03458715230226517,
    0.015908822417259216,
    0.11210630089044571,
    0.07931173592805862,
    -0.008919687941670418,
    0.0018595156725496054,
    0.01757385954260826,
    0.01932736486196518,
    0.009426715783774853,
    -0.03564339503645897,
    0.11840672791004181,
    0.07197241485118866,
    0.16397781670093536,
    0.20180743932724,
    -0.010188525542616844,
    0.42529061436653137,
    -0.04439033195376396,
    0.028798257932066917,
    -0.024045443162322044,
    0.04836198315024376,
    0.10315372049808502,
    -0.019334368407726288,
    0.066074900329113,
    -0.05850021168589592,
    0.13464850187301636,
    0.0552077516913414,
    -0.03853856772184372,
    -0.019523201510310173,
    0.13517870008945465,
    -0.006989052053540945,
    0.028201261535286903,
    0.02527109906077385,
    0.030266785994172096,
    0.43703925609588623,
    0.020612366497516632,
    -0.011615755036473274,
    0.02860068529844284,
    -0.041362740099430084,
    0.07823274284601212,
    -0.07724983245134354,
    0.12234257161617279,
    0.03724217042326927,
    -0.013658055104315281,
    0.03342217579483986,
    -0.04587850347161293,
    0.030619172379374504,
    -0.023200351744890213,
    0.039091482758522034,
    0.0802009180188179,
    0.028173502534627914,
    0.21358086168766022,
    0.07426447421312332,
    0.12227411568164825,
    0.0702630877494812,
    0.020661575719714165,
    0.41131094098091125,
    -0.02658143825829029,
    -0.018473144620656967,
    0.08175504952669144,
    0.0006962499464862049,
    0.2153032124042511,
    -0.05657164007425308,
    0.011152231134474277,
    0.050192397087812424,
    0.27296182513237,
    -0.007169280666857958,
    0.1504545509815216,
    -0.08133413642644882,
    0.061993636190891266,
    0.06167946755886078,
    -0.0015989288222044706,
    0.03284946829080582,
    0.007226115092635155,
    0.052095260471105576,
    0.006969887763261795,
    0.043634213507175446,
    -0.05270536616444588,
    0.23605488240718842,
    0.006456001661717892,
    0.19620820879936218,
    -0.06930310279130936,
    0.023853527382016182,
    -0.040342770516872406,
    0.0024650725536048412,
    -0.029971616342663765,
    0.508522093296051,
    -0.016695979982614517,
    0.3192582428455353,
    0.009550554677844048,
    0.021052753552794456,
    -0.01916891150176525,
    0.1307605504989624,
    -0.015514475293457508,
    0.12816566228866577,
    0.17103508114814758,
    0.00018376843945588917,
    -0.02388102188706398,
    0.3061349391937256,
    -0.018864935263991356,
    0.029797647148370743,
    0.006567121017724276,
    0.023136114701628685,
    0.0221941526979208,
    0.27705708146095276,
    -0.0386960431933403,
    -0.06669284403324127,
    -0.02350468933582306,
    0.04801192134618759,
    -0.04402017220854759,
    0.023932643234729767,
    -0.008652779273688793,
    0.025794539600610733,
    0.058628570288419724,
    0.01555616408586502,
    0.09422975033521652,
    0.030282609164714813,
    0.04241739958524704,
    0.006405005697160959,
    0.03372591733932495,
    -0.019592199474573135,
    0.015003867447376251,
    -0.0662100613117218,
    0.018093246966600418,
    -0.041466910392045975,
    0.21543583273887634,
    0.06494121253490448,
    0.2656717002391815,
    0.19051042199134827,
    0.09668763726949692,
    -0.010447033680975437,
    -0.0039915707893669605,
    0.0002386062260484323,
    -0.03681091591715813,
    -0.007031883578747511,
    0.10218603163957596,
    0.1439642608165741,
    0.015774330124258995,
    0.4467793107032776,
    0.00040580975473858416,
    -0.025482511147856712,
    0.042043279856443405,
    -0.06930312514305115,
    0.08637046813964844,
    0.010320190340280533,
    0.00021186175581533462,
    0.010890343226492405,
    0.7350483536720276,
    -0.09055941551923752,
    -0.024720152840018272,
    -0.013774912804365158,
    -0.03489404171705246,
    0.059380773454904556,
    -0.01789803057909012,
    -0.06169109046459198,
    0.028827665373682976,
    0.03462182730436325,
    0.441010981798172,
    0.09733743965625763,
    0.1674976646900177,
    -0.05568937584757805,
    -0.08197752386331558,
    0.04458475112915039,
    -0.026359735056757927,
    0.03248228505253792,
    0.014304328709840775,
    0.03798900544643402,
    0.11332704871892929,
    0.053812988102436066,
    -0.0044610039331018925,
    0.002763072494417429,
    0.4394238591194153,
    0.014373628422617912,
    -0.05042107403278351,
    0.25012296438217163,
    0.5395630598068237,
    0.16542594134807587,
    0.36699336767196655,
    -0.05399846285581589,
    0.4654935896396637,
    0.027359526604413986,
    -0.03297273814678192,
    0.03126814588904381,
    0.16269569098949432,
    0.17322446405887604,
    0.1692035049200058,
    0.13881513476371765,
    -0.05232389271259308,
    -0.05625195801258087,
    0.026362797245383263,
    0.1782252937555313,
    0.0617876872420311,
    -0.018390536308288574,
    0.019451206550002098,
    0.19229090213775635,
    0.007322340738028288,
    -0.00017106329323723912,
    0.20729385316371918,
    0.008417999371886253,
    0.05256897956132889,
    0.06996353715658188,
    0.019584165886044502,
    0.07841426134109497,
    0.02417057752609253,
    0.02544092759490013,
    -0.02752002887427807,
    -0.04534604772925377,
    0.1298067420721054,
    -0.028923451900482178,
    0.0643780454993248,
    -0.027623670175671577,
    0.5607196688652039,
    -0.007701790425926447,
    0.060853712260723114,
    0.2072930783033371,
    0.7431402802467346,
    0.032769378274679184,
    0.14457254111766815,
    0.022702595219016075,
    -0.009668521583080292,
    -0.0064052739180624485,
    0.005445585586130619,
    0.007712016813457012,
    -0.08574312925338745,
    0.0902736708521843,
    -0.014891412109136581,
    0.1263628900051117,
    -0.026003945618867874,
    -0.014346398413181305,
    0.03841283917427063,
    0.080800361931324,
    0.12182775139808655,
    0.026898570358753204,
    0.07896830886602402,
    0.06142091378569603,
    0.6589785814285278,
    0.08593917638063431,
    -0.0026892777532339096,
    0.008941245265305042,
    0.01637478917837143,
    0.17001484334468842,
    0.013625695370137691,
    0.008502705954015255,
    0.2627941071987152,
    -0.048671312630176544,
    0.016809837892651558,
    -0.07140399515628815,
    0.12477970868349075,
    0.0313858725130558,
    0.061598386615514755,
    0.0640006735920906,
    0.028401754796504974,
    0.24868150055408478,
    0.2168934941291809,
    0.3344763517379761,
    0.02203676663339138,
    0.01998678408563137,
    -0.01373958308249712,
    0.10140489041805267,
    -0.039255738258361816,
    -0.013618755154311657,
    -0.012051268480718136,
    0.01467037945985794,
    -0.038770969957113266,
    0.4952315092086792,
    -0.00011524686851771548,
    0.00040883629117161036,
    -0.02754627913236618,
    -0.0013074143789708614,
    0.09646140784025192,
    0.01317546982318163,
    0.4591313600540161,
    -0.019637666642665863,
    0.021707680076360703,
    0.06451556086540222,
    0.04431302100419998,
    0.12049463391304016,
    0.06480707973241806,
    0.15770168602466583,
    0.015728849917650223,
    -0.027423901483416557,
    0.14743146300315857,
    0.0673452764749527,
    0.17907428741455078,
    -0.022689877077937126,
    0.11584789305925369,
    0.3092474043369293,
    0.044835418462753296,
    0.12262500077486038,
    -0.028739212080836296,
    -0.01880059950053692,
    0.47878214716911316,
    -0.01824241317808628
  ],
  "clap_audio_embedding_mean": [
    -0.0077400971204042435,
    0.024251723662018776,
    -0.055797576904296875,
    0.009144997224211693,
    -0.03558918461203575,
    0.04774918034672737,
    -0.016062628477811813,
    -0.01521971169859171,
    -0.07163985818624496,
    0.018334871158003807,
    0.003898071125149727,
    0.03103645332157612,
    -0.020146412774920464,
    0.03171136602759361,
    0.022754093632102013,
    -0.024676630273461342,
    -0.0796220675110817,
    0.0585603304207325,
    -0.030439412221312523,
    0.10226449370384216,
    -0.047585707157850266,
    0.021632324904203415,
    0.014728149399161339,
    -0.050727423280477524,
    0.02827232889831066,
    -0.012026130221784115,
    -0.0007470687269233167,
    0.008173794485628605,
    -0.02181604877114296,
    -0.0054218047298491,
    0.06538950651884079,
    0.10371511429548264,
    0.02020445093512535,
    0.02905864827334881,
    0.03954935818910599,
    0.07140786945819855,
    0.03556670621037483,
    0.014754646457731724,
    0.03554399311542511,
    -0.01230328157544136,
    0.07695507258176804,
    -0.05793195590376854,
    0.008638815023005009,
    0.03293630853295326,
    0.00028713891515508294,
    -0.04843142628669739,
    0.0324213020503521,
    -0.005689437035471201,
    -0.01788441091775894,
    -0.013241385109722614,
    -0.028781546279788017,
    -0.013602862134575844,
    0.015537725761532784,
    -0.08483603596687317,
    -0.008952213451266289,
    -0.029604794457554817,
    0.025921305641531944,
    0.002499308902770281,
    0.08850907534360886,
    -0.017769794911146164,
    -0.028922660276293755,
    -0.0007338545401580632,
    0.01111647766083479,
    0.03904334828257561,
    -0.028402728959918022,
    -0.00012399355182424188,
    0.03207564353942871,
    -0.04189214110374451,
    -0.030675189569592476,
    -0.03565897047519684,
    0.05771960690617561,
    -0.015602414496243,
    0.0832124873995781,
    0.025602951645851135,
    0.004160167183727026,
    0.05850949510931969,
    0.01292724721133709,
    -0.0722055435180664,
    -0.10324515402317047,
    -0.06383887678384781,
    -0.05824047327041626,
    0.018766719847917557,
    -0.09200088679790497,
    0.00045900442637503147,
    0.03849053382873535,
    -0.04094349965453148,
    -0.061661142855882645,
    0.01736443117260933,
    0.06317391991615295,
    0.019680660218000412,
    0.05949774384498596,
    0.007477715145796537,
    -0.04309123381972313,
    0.05481342971324921,
    0.04565265029668808,
    -0.0071216123178601265,
    0.028357120230793953,
    -0.019774816930294037,
    -0.009770277887582779,
    0.019125746563076973,
    -0.02510247565805912,
    0.01799619197845459,
    -0.011928842402994633,
    -0.08308947831392288,
    0.049251336604356766,
    0.032357413321733475,
    -0.02891402319073677,
    -0.03839030861854553,
    0.015109769068658352,
    -0.022268695756793022,
    -0.0872877836227417,
    0.048833079636096954,
    0.03514593094587326,
    -0.009647599421441555,
    -0.10470971465110779,
    -0.005014078225940466,
    -0.03324832022190094,
    0.0577567033469677,
    0.040990039706230164,
    -0.010918952524662018,
    0.04413880780339241,
    0.09317813813686371,
    0.019703365862369537,
    0.02220264822244644,
    -0.09016772359609604,
    -0.05870350822806358,
    0.004836238455027342,
    -0.015628047287464142,
    0.0204471368342638,
    0.0027822074480354786,
    -0.005233277566730976,
    0.027706708759069443,
    0.03769685700535774,
    -0.07010353356599808,
    -0.007765502668917179,
    -0.027738941833376884,
    -0.04472414031624794,
    0.016583241522312164,
    0.02940583974123001,
    -0.10900940746068954,
    0.007633172441273928,
    0.021674521267414093,
    -0.04625315964221954,
    0.005186827853322029,
    0.011688931845128536,
    -0.007211292628198862,
    0.030896201729774475,
    -0.04117203503847122,
    -0.06176074966788292,
    0.025341162458062172,
    0.013111989013850689,
    -0.023430583998560905,
    -0.007394071668386459,
    -0.021188076585531235,
    0.056420452892780304,
    -0.01834924705326557,
    -0.06285057961940765,
    0.010976794175803661,
    -0.022458959370851517,
    0.017157692462205887,
    -0.04881565272808075,
    0.03676842898130417,
    0.10980153828859329,
    -0.028656458482146263,
    -0.04898139834403992,
    -0.03019065596163273,
    -0.02075292356312275,
    -0.003583292244002223,
    -0.013847015798091888,
    -0.006313165184110403,
    -0.08661043643951416,
    -0.0721970871090889,
    0.020396694540977478,
    0.015680616721510887,
    0.003810723777860403,
    -0.055656298995018005,
    0.07953570783138275,
    0.05060314014554024,
    0.017581455409526825,
    0.0410151332616806,
    0.015393629670143127,
    0.046742502599954605,
    0.07456892728805542,
    -0.07030301541090012,
    0.06599078327417374,
    0.06779304891824722,
    -0.04143780097365379,
    0.02821086347103119,
    -0.042798563838005066,
    -0.0587473101913929,
    -0.04515849053859711,
    -0.05237943306565285,
    -0.057128891348838806,
    0.06725626438856125,
    0.03514319658279419,
    -0.010668790899217129,
    0.043990492820739746,
    0.03262598440051079,
    -0.026045221835374832,
    0.007956885732710361,
    0.0006858500419184566,
    -0.028454193845391273,
    0.08310817927122116,
    0.029447397217154503,
    0.014631285332143307,
    -0.02030678652226925,
    -0.02078844979405403,
    -0.02620992623269558,
    0.03239523246884346,
    0.0196048803627491,
    -0.024761715903878212,
    0.009079484269022942,
    0.005854315590113401,
    -0.025937581434845924,
    -0.015964603051543236,
    -0.02668682113289833,
    0.02297760359942913,
    0.004056579899042845,
    0.007463593035936356,
    0.079436294734478,
    0.0661252960562706,
    -0.0490683987736702,
    -0.013377266004681587,
    0.026348982006311417,
    -0.006673084106296301,
    -0.012244545854628086,
    0.07026047259569168,
    -0.005551821086555719,
    -0.019110359251499176,
    -0.01710674911737442,
    -0.005144546274095774,
    -0.08987027406692505,
    0.03868556022644043,
    0.06616024672985077,
    0.0038013961166143417,
    0.030469214543700218,
    -0.007787150330841541,
    -0.0204059649258852,
    0.02509232796728611,
    -0.008414638228714466,
    0.01681174524128437,
    -0.022682197391986847,
    -0.004146697465330362,
    0.0160423144698143,
    0.004313919693231583,
    -0.02921297587454319,
    0.08414742350578308,
    0.015547219663858414,
    -0.01782103255391121,
    0.04562483727931976,
    0.01959219016134739,
    -0.00283039384521544,
    -0.016007497906684875,
    -0.020641371607780457,
    -0.04386541619896889,
    -0.015404824167490005,
    -0.012824330478906631,
    0.029287023469805717,
    0.004443963523954153,
    -0.04121550917625427,
    -0.026671184226870537,
    0.07755237072706223,
    0.034945957362651825,
    0.026750700548291206,
    0.04220590740442276,
    -0.0073569281958043575,
    0.05313454568386078,
    0.00846800021827221,
    0.036170605570077896,
    0.047874078154563904,
    0.17435112595558167,
    0.03876299038529396,
    0.03550077602267265,
    0.012697274796664715,
    -0.037858229130506516,
    -0.05889023095369339,
    -0.03871013969182968,
    -0.06936759501695633,
    -0.09455981850624084,
    -0.004180653486400843,
    0.06544811278581619,
    -0.03153067082166672,
    -0.061207115650177,
    -0.010524071753025055,
    -0.05510362610220909,
    0.04256344214081764,
    0.017639633268117905,
    -0.021920330822467804,
    0.028384901583194733,
    -0.016007866710424423,
    0.027671584859490395,
    0.07064619660377502,
    0.025853509083390236,
    -0.0007935469038784504,
    -0.03554835915565491,
    -0.04389362782239914,
    0.0015026688342913985,
    -0.00012751530448440462,
    -0.019187400117516518,
    -0.010674113407731056,
    -0.07041974365711212,
    -0.008652117103338242,
    0.0010433028219267726,
    -0.053297486156225204,
    0.011257962323725224,
    -0.028728006407618523,
    0.010423178784549236,
    -0.015273595228791237,
    -0.031846802681684494,
    0.04494524374604225,
    -0.004570554941892624,
    -0.017632639035582542,
    0.007537872530519962,
    0.014593825675547123,
    -0.03630557656288147,
    0.04354006052017212,
    -0.10537263005971909,
    -0.00862792693078518,
    0.011543219909071922,
    -0.007428386714309454,
    0.0428466834127903,
    -0.05217653512954712,
    0.014860644936561584,
    -0.12978583574295044,
    0.07893708348274231,
    -0.02550809644162655,
    -0.033528346568346024,
    0.06795641034841537,
    -0.028485560789704323,
    0.07023564726114273,
    0.013659766875207424,
    0.045124027878046036,
    -0.019471097737550735,
    0.05709686130285263,
    -0.011007800698280334,
    -0.027325676754117012,
    -0.010103855282068253,
    0.0013572500320151448,
    0.006763024255633354,
    0.054788555949926376,
    0.025106385350227356,
    -0.0013664676807820797,
    -0.045836977660655975,
    0.021083110943436623,
    -0.020628800615668297,
    -0.04287548363208771,
    0.0222733486443758,
    0.00908255111426115,
    -0.007632607594132423,
    -0.031150339171290398,
    -0.013066149316728115,
    -0.05946851521730423,
    0.0044442107900977135,
    0.04453549534082413,
    0.10269681364297867,
    -0.045292023569345474,
    0.010517274960875511,
    0.1092628613114357,
    0.01087227277457714,
    -0.05344747379422188,
    0.12033049762248993,
    0.04353535175323486,
    -0.06813204288482666,
    0.06782794743776321,
    0.0252827275544405,
    -0.04345162212848663,
    0.023253386840224266,
    0.054633479565382004,
    0.0681203082203865,
    0.02761250175535679,
    0.01043663639575243,
    0.008682244457304478,
    0.017105257138609886,
    -0.07336311787366867,
    -0.022878147661685944,
    0.026125110685825348,
    -0.055560335516929626,
    -0.027006905525922775,
    0.0016381994355469942,
    -0.012547665275633335,
    0.023246683180332184,
    -0.019504746422171593,
    0.014934409409761429,
    -0.055846501141786575,
    -0.005700152367353439,
    0.010401230305433273,
    0.0110853910446167,
    -0.05601120740175247,
    0.016698241233825684,
    -0.033564627170562744,
    0.0507475920021534,
    -0.11961928755044937,
    0.0026572728529572487,
    -0.08436821401119232,
    -0.017308486625552177,
    0.018257251009345055,
    0.02022462524473667,
    0.027938589453697205,
    -0.005051088985055685,
    -0.014236261136829853,
    -0.0023526684381067753,
    0.016396235674619675,
    0.03513617068529129,
    -0.015596008859574795,
    -0.022309018298983574,
    -0.02656148187816143,
    -0.011766236275434494,
    0.04674658924341202,
    0.03494304418563843,
    -0.02065885253250599,
    -0.03696721792221069,
    0.046113546937704086,
    0.05375678092241287,
    -0.01140550896525383,
    -0.06572340428829193,
    0.16411258280277252,
    0.02015487477183342,
    0.05084608495235443,
    0.03245169669389725,
    -0.05799606814980507,
    0.03175344690680504,
    0.005072115920484066,
    0.007689836900681257,
    0.06221194565296173,
    0.011000568978488445,
    0.06592359393835068,
    -0.030292194336652756,
    0.019299454987049103,
    0.05872918665409088,
    0.03683788329362869,
    -0.001712716300971806,
    -0.04271189495921135,
    0.06425941735506058,
    0.012747414410114288,
    0.056267283856868744,
    -0.005672069266438484,
    -0.015288586728274822,
    -0.08926152437925339,
    -0.027948036789894104,
    0.0014541747514158487,
    0.021118273958563805,
    0.06301138550043106,
    0.0274239219725132,
    0.01905202865600586,
    -0.004078282043337822,
    -0.02349645271897316,
    -0.08060305565595627,
    -0.050592243671417236,
    -0.02047044411301613,
    -0.07800232619047165,
    -0.014395395293831825,
    0.032135993242263794,
    -0.010188634507358074,
    0.043027255684137344,
    0.012076220475137234,
    0.015813980251550674,
    0.006116628646850586,
    0.02925548516213894,
    -0.08969464153051376,
    -0.035043612122535706,
    -0.06292152404785156,
    0.05254511535167694,
    0.006788197904825211,
    -0.05508454516530037,
    0.036920975893735886,
    0.03237389028072357,
    -0.046201568096876144,
    0.04888178035616875,
    -0.09462258219718933,
    0.015577733516693115,
    0.01687953807413578,
    0.039278265088796616,
    0.02234870009124279,
    0.05003732070326805,
    0.055740419775247574,
    -0.01397920586168766,
    -0.020855320617556572,
    -0.001627735560759902,
    0.02597421407699585,
    0.06919971853494644,
    0.1275041103363037,
    0.06377001851797104,
    0.02269514836370945,
    -0.04569489508867264,
    0.09104004502296448,
    -0.023657716810703278,
    0.01747448928654194,
    -0.017165714874863625,
    0.002731658983975649,
    -0.030844030901789665,
    0.030074389651417732,
    0.09420368075370789,
    0.07785812765359879,
    -0.003055830951780081,
    0.006520468275994062,
    0.01436871662735939,
    -0.0409214086830616,
    0.029398296028375626,
    -0.05630025267601013,
    0.03235586732625961,
    -0.035496603697538376,
    0.06553871929645538,
    -0.05808984860777855,
    -0.030737081542611122,
    -0.02054774761199951,
    0.009190641343593597,
    0.0642307922244072,
    -0.026606997475028038,
    0.06206245720386505,
    0.03581558167934418,
    0.08555717766284943,
    0.04400496557354927
  ],
  "analyzed_at_utc": "2026-04-18T14:10:36.647135+00:00"
}